duckduckgo_api_haystack/__init__.py
duckduckgo_api_haystack/duckduckgoapi.py
duckduckgo_api_haystack-0.1.15.dist-info/licenses/LICENSE
duckduckgo_api_haystack-0.1.15.dist-info/METADATA
duckduckgo_api_haystack-0.1.15.dist-info/WHEEL
duckduckgo_api_haystack-0.1.15.dist-info/top_level.txt
duckduckgo_api_haystack-0.1.15.dist-info/RECORD
