Metadata-Version: 2.4
Name: duckduckgo-api-haystack
Version: 0.1.15
Summary: A Haystack component integrating Duckduckgo API for WebSearch
Author-email: Giovanni Alzetta <giovannialzetta@gmail.com>
License: Apache-2.0
Project-URL: Homepage, https://github.com/GivAlz/duckduckgo_api_websearch
Classifier: Programming Language :: Python :: 3
Classifier: Programming Language :: Python :: 3.8
Classifier: Programming Language :: Python :: 3.9
Classifier: Programming Language :: Python :: 3.10
Classifier: Programming Language :: Python :: 3.11
Classifier: Programming Language :: Python :: 3.12
Classifier: Operating System :: OS Independent
Requires-Python: >=3.8
License-File: LICENSE
Requires-Dist: duckduckgo-search<8; python_version <= "3.8"
Requires-Dist: duckduckgo-search~=8.0.1; python_version > "3.8"
Requires-Dist: haystack-ai
Dynamic: license-file
